plotly_gtk/__init__.py
plotly_gtk/_chart.py
plotly_gtk/_version.py
plotly_gtk/chart.py
plotly_gtk/demo.py
plotly_gtk/webview.py
plotly_gtk/utils/__init__.py
plotly_gtk/utils/plot-schema.json
plotly_gtk/utils/plotly_types.py
plotly_gtk/utils/ticks.py
plotly_gtk/utils/templates/ggplot2.json
plotly_gtk/utils/templates/gridon.json
plotly_gtk/utils/templates/plotly.json
plotly_gtk/utils/templates/plotly_dark.json
plotly_gtk/utils/templates/plotly_white.json
plotly_gtk/utils/templates/presentation.json
plotly_gtk/utils/templates/seaborn.json
plotly_gtk/utils/templates/simple_white.json
plotly_gtk/utils/templates/xgridoff.json
plotly_gtk/utils/templates/ygridoff.json
plotly_gtk/widgets/__init__.py
plotly_gtk/widgets/annotation.py
plotly_gtk/widgets/axis_title.py
plotly_gtk/widgets/base.py
plotly_gtk/widgets/legend.py
plotly_gtk/widgets/updatemenus.py
plotly_gtk-0.3.2.dist-info/LICENSE
plotly_gtk-0.3.2.dist-info/METADATA
plotly_gtk-0.3.2.dist-info/WHEEL
plotly_gtk-0.3.2.dist-info/top_level.txt
plotly_gtk-0.3.2.dist-info/RECORD
