Metadata-Version: 2.1
Name: plotly-gtk
Version: 0.3.2
License-File: LICENSE
Requires-Dist: numpy <2.0
Requires-Dist: pygobject
Requires-Dist: pandas
Requires-Dist: prefixed
Provides-Extra: dev
Requires-Dist: plotly-gtk[doc,lint,test] ; extra == 'dev'
Provides-Extra: doc
Requires-Dist: pylint ; extra == 'doc'
Requires-Dist: sphinx ; extra == 'doc'
Requires-Dist: sphinx-pyreverse ; extra == 'doc'
Requires-Dist: pydata-sphinx-theme ; extra == 'doc'
Requires-Dist: sphinx-rtd-theme ; extra == 'doc'
Requires-Dist: plotly ; extra == 'doc'
Provides-Extra: lint
Requires-Dist: black ; extra == 'lint'
Requires-Dist: isort ; extra == 'lint'
Requires-Dist: flake8 ; extra == 'lint'
Requires-Dist: flake8-pyproject ; extra == 'lint'
Requires-Dist: flake8-pylint ; extra == 'lint'
Requires-Dist: flake8-json ; extra == 'lint'
Requires-Dist: flake8-bugbear ; extra == 'lint'
Requires-Dist: mypy ; extra == 'lint'
Requires-Dist: mypy-json-report ; extra == 'lint'
Requires-Dist: pygobject-stubs ; extra == 'lint'
Requires-Dist: deptry ; extra == 'lint'
Provides-Extra: test
Requires-Dist: plotly ; extra == 'test'
Requires-Dist: pytest ; extra == 'test'
Requires-Dist: pillow ; extra == 'test'
Requires-Dist: selenium ; extra == 'test'
Requires-Dist: pytest-subtests ; extra == 'test'
Requires-Dist: pytest-cov ; extra == 'test'
Requires-Dist: pytest-html ; extra == 'test'
